pickledonion/__init__.py
pickledonion/decorators.py
pickledonion/hashing.py
pickledonion-1.0.4.dist-info/LICENSE
pickledonion-1.0.4.dist-info/METADATA
pickledonion-1.0.4.dist-info/WHEEL
pickledonion-1.0.4.dist-info/top_level.txt
pickledonion-1.0.4.dist-info/RECORD
