Metadata-Version: 2.1
Name: pickledonion
Version: 1.0.4
Summary: Python pickle disk caching which encourages configuration on the outer layers of an "onion" architecture
Home-page: https://github.com/rcgale/pickledonion
Author: Robert Gale
Author-email: rcgale@gmail.com
License-File: LICENSE
